Metadata-Version: 2.1
Name: lib-dzne-levenshtein
Version: 0.1.0
Summary: Libary for dealing with the levenshtein-program. 
Author-email: Johannes Horler <johannes.horler@dzne.de>
License: Copyright © 2022 Johannes Horler
Keywords: levenshtein
Classifier: License :: OSI Approved :: MIT License
Classifier: Programming Language :: Python
Classifier: Programming Language :: Python :: 3
Requires-Python: >=3.11
License-File: LICENSE
Requires-Dist: numpy (>=1.24.2)
